easyaws
