Metadata-Version: 1.1
Name: easy-aws
Version: 1.0.6
Summary: Deploying django-projects to Amazon AWS
Home-page: https://bitbucket.org/dlis/easy-aws
Author: UNKNOWN
Author-email: UNKNOWN
License: MIT
Keywords: deploy django amazon aws ec2 elb pycharm
Platform: UNKNOWN
Classifier: Development Status :: 1 - Planning
Classifier: Intended Audience :: Developers
Classifier: Topic :: Software Development
Classifier: Topic :: Utilities
Classifier: License :: OSI Approved :: MIT License
Classifier: Programming Language :: Python :: 3
Classifier: Programming Language :: Python :: 3.2
Classifier: Programming Language :: Python :: 3.3
Classifier: Programming Language :: Python :: 3.4
